fc_functions_framework-0.0.29-py3.8-nspkg.pth
functions_framework/__init__.py
functions_framework/__main__.py
functions_framework/_cli.py
functions_framework/_function_registry.py
functions_framework/background_event.py
functions_framework/event_conversion.py
functions_framework/exceptions.py
functions_framework/_http/__init__.py
functions_framework/_http/flask.py
functions_framework/_http/gunicorn.py
functions_framework/_of/__init__.py
functions_framework/_of/dapr.py
functions_framework/_of/v2/__init__.py
functions_framework/_of/v2/context.py
google/cloud/functions/__init__.py
google/cloud/functions/context.py
google/cloud/functions_v1/__init__.py
google/cloud/functions_v1/context.py
google/cloud/functions_v1beta2/__init__.py
google/cloud/functions_v1beta2/context.py
fc_functions_framework-0.0.29.dist-info/METADATA
fc_functions_framework-0.0.29.dist-info/WHEEL
fc_functions_framework-0.0.29.dist-info/entry_points.txt
fc_functions_framework-0.0.29.dist-info/namespace_packages.txt
fc_functions_framework-0.0.29.dist-info/top_level.txt
fc_functions_framework-0.0.29.dist-info/RECORD
